orderedset/__init__.py
orderedset/orderedset.py
proxyorderedset-0.3.5.dist-info/LICENSE
proxyorderedset-0.3.5.dist-info/METADATA
proxyorderedset-0.3.5.dist-info/WHEEL
proxyorderedset-0.3.5.dist-info/top_level.txt
proxyorderedset-0.3.5.dist-info/RECORD
