Metadata-Version: 2.1
Name: proxyorderedset
Version: 0.3.5
Summary: A simple implementation of ordered sets as a proxy to Python's standard dict class.
Home-page: https://github.com/rindPHI/proxyorderedset
Author: Dominic Steinhöfel
Author-email: Dominic Steinhöfel <dominic.steinhoefel@cispa.de>
License: This is free and unencumbered software released into the public domain.
Project-URL: Homepage, https://github.com/rindPHI/proxyorderedset/
Project-URL: Bug Tracker, https://github.com/rindPHI/proxyorderedset/issues
Classifier: Intended Audience :: Developers
Classifier: License :: OSI Approved :: The Unlicense (Unlicense)
Classifier: Programming Language :: Python :: 3
Classifier: Operating System :: OS Independent
Classifier: Topic :: Software Development :: Libraries
Requires-Python: >=3.10
License-File: LICENSE
Requires-Dist: frozendict >=2.3.2
Provides-Extra: test
Requires-Dist: pytest-cov >=3.0.0 ; extra == 'test'
Requires-Dist: pytest-forked >=1.3.0 ; extra == 'test'
Requires-Dist: pytest-html >=3.1.1 ; extra == 'test'
Requires-Dist: pytest-profiling >=1.7.0 ; extra == 'test'
Requires-Dist: pytest-pycharm >=0.7.0 ; extra == 'test'
Requires-Dist: pytest-rerunfailures >=10.2 ; extra == 'test'
Requires-Dist: pytest-xdist >=2.4.0 ; extra == 'test'
Requires-Dist: pytest >=7.1.2 ; extra == 'test'
